pykronecker/__init__.py
pykronecker/base.py
pykronecker/block.py
pykronecker/composite.py
pykronecker/fast_math.py
pykronecker/operators.py
pykronecker/utils.py
pykronecker-0.1.3.dist-info/LICENSE
pykronecker-0.1.3.dist-info/METADATA
pykronecker-0.1.3.dist-info/WHEEL
pykronecker-0.1.3.dist-info/top_level.txt
pykronecker-0.1.3.dist-info/RECORD
