Metadata-Version: 2.1
Name: pykronecker
Version: 0.1.3
Summary: Tools for performing efficient Kronecker product-based matrix operations
Home-page: https://github.com/nickelnine37/pykronecker
Author: nickelnine37
License: MIT
Project-URL: Bug Tracker, https://github.com/nickelnine37/pykronecker/issues
Platform: unix
Platform: linux
Platform: osx
Platform: cygwin
Platform: win32
Classifier: Programming Language :: Python :: 3
Classifier: Programming Language :: Python :: 3 :: Only
Classifier: Programming Language :: Python :: 3.7
Classifier: Programming Language :: Python :: 3.8
Classifier: Programming Language :: Python :: 3.9
Classifier: Programming Language :: Python :: 3.10
Classifier: License :: OSI Approved :: MIT License
Classifier: Operating System :: OS Independent
Requires-Python: >=3.7
License-File: LICENSE
Requires-Dist: numpy (>=1.10)
Provides-Extra: jax
Requires-Dist: jax (>=0.2.7) ; extra == 'jax'
Requires-Dist: jaxlib (>=0.1.57) ; extra == 'jax'
Provides-Extra: testing
Requires-Dist: pytest (>=6.0) ; extra == 'testing'
Requires-Dist: pytest-cov (>=2.0) ; extra == 'testing'
Requires-Dist: tox (>=3.24) ; extra == 'testing'
Requires-Dist: jax (>=0.2.7) ; extra == 'testing'
Requires-Dist: jaxlib (>=0.1.57) ; extra == 'testing'
